dash_svg/Animate.py
dash_svg/Circle.py
dash_svg/ClipPath.py
dash_svg/Defs.py
dash_svg/Desc.py
dash_svg/Ellipse.py
dash_svg/FeBlend.py
dash_svg/FeColorMatrix.py
dash_svg/FeComponentTransfer.py
dash_svg/FeComposite.py
dash_svg/FeConvolveMatrix.py
dash_svg/FeDiffuseLighting.py
dash_svg/FeDisplacementMap.py
dash_svg/FeDistantLight.py
dash_svg/FeDropShadow.py
dash_svg/FeFlood.py
dash_svg/FeFuncA.py
dash_svg/FeFuncB.py
dash_svg/FeFuncG.py
dash_svg/FeFuncR.py
dash_svg/FeGaussianBlur.py
dash_svg/FeImage.py
dash_svg/FeMerge.py
dash_svg/FeMergeNode.py
dash_svg/FeMorphology.py
dash_svg/FeOffset.py
dash_svg/FePointLight.py
dash_svg/FeSpecularLighting.py
dash_svg/FeSpotLight.py
dash_svg/FeTile.py
dash_svg/FeTurbulence.py
dash_svg/Filter.py
dash_svg/ForeignObject.py
dash_svg/G.py
dash_svg/Image.py
dash_svg/Line.py
dash_svg/LinearGradient.py
dash_svg/Marker.py
dash_svg/Mask.py
dash_svg/Metadata.py
dash_svg/Path.py
dash_svg/Pattern.py
dash_svg/Polygon.py
dash_svg/Polyline.py
dash_svg/RadialGradient.py
dash_svg/Rect.py
dash_svg/Stop.py
dash_svg/Svg.py
dash_svg/Switch.py
dash_svg/Symbol.py
dash_svg/Text.py
dash_svg/TextPath.py
dash_svg/Tspan.py
dash_svg/Use.py
dash_svg/View.py
dash_svg/__init__.py
dash_svg/_imports_.py
dash_svg/dash_svg.dev.js
dash_svg/dash_svg.dev.js.map
dash_svg/dash_svg.min.js
dash_svg/dash_svg.min.js.map
dash_svg/metadata.json
dash_svg/package-info.json
dash_svg-0.0.12.dist-info/LICENSE
dash_svg-0.0.12.dist-info/METADATA
dash_svg-0.0.12.dist-info/WHEEL
dash_svg-0.0.12.dist-info/top_level.txt
dash_svg-0.0.12.dist-info/RECORD
