Metadata-Version: 2.1
Name: dash_svg
Version: 0.0.12
Summary: SVG support library for Plotly/Dash
Home-page: UNKNOWN
Author: Steve Jones <jonesst2608@gmail.com>
License: MIT
Platform: UNKNOWN
Classifier: Framework :: Dash
License-File: LICENSE
